jutge/util/__init__.py
jutge_util-1.3.3.dist-info/DESCRIPTION.rst
jutge_util-1.3.3.dist-info/METADATA
jutge_util-1.3.3.dist-info/RECORD
jutge_util-1.3.3.dist-info/WHEEL
jutge_util-1.3.3.dist-info/metadata.json
jutge_util-1.3.3.dist-info/top_level.txt
