Metadata-Version: 2.0
Name: jutge-util
Version: 1.3.3
Summary: Common utilities for Jutge.org's scripts
Home-page: https://github.com/jutge-org/jutge-util
Author: Jordi Petit et al
Author-email: jpetit@cs.upc.edu
License: Apache
Download-URL: https://github.com/jutge-org/jutge-util/tarball/1.3.3
Keywords: jutge,jutge.org,util
Platform: UNKNOWN
Requires-Dist: chardet
Requires-Dist: pyyaml
